mcp_server_rabbitmq/__init__.py
mcp_server_rabbitmq/admin.py
mcp_server_rabbitmq/connection.py
mcp_server_rabbitmq/constant.py
mcp_server_rabbitmq/handlers.py
mcp_server_rabbitmq/server.py
mseep_mcp_server_rabbitmq-2.0.2.dist-info/METADATA
mseep_mcp_server_rabbitmq-2.0.2.dist-info/WHEEL
mseep_mcp_server_rabbitmq-2.0.2.dist-info/entry_points.txt
mseep_mcp_server_rabbitmq-2.0.2.dist-info/licenses/LICENSE
mseep_mcp_server_rabbitmq-2.0.2.dist-info/RECORD
